cli/__init__.py
cli/commands.py
cli/main.py
config/__init__.py
config/config.yaml
config/__pycache__/__init__.cpython-313.pyc
core/__init__.py
core/config_manager.py
core/initialization.py
resources/__init__.py
resources/graphshift-logo.png
resources/gs-analyzer.jar
resources/__pycache__/__init__.cpython-313.pyc
services/__init__.py
services/analysis_service.py
services/base_analyzer.py
services/cancellation_service.py
services/clone_service.py
services/health_service.py
services/help_service.py
services/output_formatter.py
services/progress_reporter.py
services/scm_service.py
services/types.py
templates/__init__.py
templates/organization_report.html
templates/single_repo_report.html
templates/__pycache__/__init__.cpython-313.pyc
graphshift_discovery-1.0.0.dist-info/METADATA
graphshift_discovery-1.0.0.dist-info/WHEEL
graphshift_discovery-1.0.0.dist-info/entry_points.txt
graphshift_discovery-1.0.0.dist-info/top_level.txt
graphshift_discovery-1.0.0.dist-info/RECORD
