Metadata-Version: 2.4
Name: graphshift-discovery
Version: 1.0.0
Summary: AI-Augmented Java Migration Assistant - Open Source Edition
Home-page: https://github.com/graphshift-dev/discovery
Author: GraphShift Team
Author-email: contact@graphshift.dev
Project-URL: Bug Reports, https://github.com/graphshift-dev/discovery/issues
Project-URL: Source, https://github.com/graphshift-dev/discovery
Project-URL: Documentation, https://docs.graphshift.dev
Keywords: java migration refactoring analysis ast deprecation
Classifier: Development Status :: 5 - Production/Stable
Classifier: Intended Audience :: Developers
Classifier: License :: OSI Approved :: Apache Software License
Classifier: Operating System :: OS Independent
Classifier: Programming Language :: Python :: 3
Classifier: Programming Language :: Python :: 3.8
Classifier: Programming Language :: Python :: 3.9
Classifier: Programming Language :: Python :: 3.10
Classifier: Programming Language :: Python :: 3.11
Classifier: Programming Language :: Python :: 3.12
Classifier: Programming Language :: Java
Classifier: Topic :: Software Development :: Libraries :: Python Modules
Classifier: Topic :: Software Development :: Quality Assurance
Classifier: Topic :: System :: Software Distribution
Requires-Python: >=3.8
Requires-Dist: pyyaml>=6.0
Requires-Dist: pathlib>=1.0.0
Requires-Dist: aiohttp>=3.8.0
Requires-Dist: appdirs>=1.4.4
Requires-Dist: setuptools
Provides-Extra: dev
Requires-Dist: pytest>=7.0.0; extra == "dev"
Requires-Dist: pytest-asyncio>=0.21.0; extra == "dev"
Requires-Dist: pytest-cov>=4.0.0; extra == "dev"
Requires-Dist: black>=22.0.0; extra == "dev"
Requires-Dist: flake8>=4.0.0; extra == "dev"
Requires-Dist: mypy>=0.991; extra == "dev"
Dynamic: author
Dynamic: author-email
Dynamic: classifier
Dynamic: description
Dynamic: description-content-type
Dynamic: home-page
Dynamic: keywords
Dynamic: project-url
Dynamic: provides-extra
Dynamic: requires-dist
Dynamic: requires-python
Dynamic: summary
